LICENSE.txt
MANIFEST.in
setup.cfg
setup.py
FHR_DB.egg-info/PKG-INFO
FHR_DB.egg-info/SOURCES.txt
FHR_DB.egg-info/dependency_links.txt
FHR_DB.egg-info/entry_points.txt
FHR_DB.egg-info/requires.txt
FHR_DB.egg-info/top_level.txt
fhr_db/__init__.py
fhr_db/fhr_db.py