Metadata-Version: 1.1
Name: FHR-DB
Version: 1.0.2
Summary: Schemaless mysql db datalayer
Home-page: https://github.com/nkordulla/FHR-DB
Author: Nikolai Kordulla
Author-email: kordulla@googlemail.com
License: MIT
Download-URL: https://github.com/nkordulla/FHR-DB/tarball/1.0.2
Keywords: mysql orm database layer schemaless
Platform: UNKNOWN
Classifier: Development Status :: 3 - Alpha
Classifier: Intended Audience :: Developers
Classifier: Topic :: Software Development :: Build Tools
Classifier: License :: OSI Approved :: MIT License
Classifier: Programming Language :: Python :: 2
Classifier: Programming Language :: Python :: 2.6
Classifier: Programming Language :: Python :: 2.7
Classifier: Programming Language :: Python :: 3
Classifier: Programming Language :: Python :: 3.3
Classifier: Programming Language :: Python :: 3.4
Classifier: Programming Language :: Python :: 3.5
